dop1/__init__.py
dop1/__main__.py
dop1/cli.py
dop1/exceptions.py
dop1/predictor.py
dop1/utils.py
dop1-0.1.0.dist-info/METADATA
dop1-0.1.0.dist-info/WHEEL
dop1-0.1.0.dist-info/top_level.txt
dop1-0.1.0.dist-info/RECORD
