Metadata-Version: 2.4
Name: dop1
Version: 0.1.0
Summary: Diabetes Osteoporosis Prediction Package - AI-powered analysis for diabetes complicated with osteoporosis
Home-page: https://github.com/dop-research/dop1
Author: DOP Research Team
Author-email: DOP Research Team <research@dop.com>
Project-URL: Homepage, https://github.com/dop-research/dop1
Project-URL: Repository, https://github.com/dop-research/dop1
Project-URL: Documentation, https://dop1.readthedocs.io
Project-URL: Issues, https://github.com/dop-research/dop1/issues
Requires-Python: >=3.8
Requires-Dist: pandas>=1.3.0
Requires-Dist: openai>=1.0.0
Requires-Dist: numpy>=1.21.0
Requires-Dist: scikit-learn>=1.0.0
Requires-Dist: matplotlib>=3.5.0
Requires-Dist: seaborn>=0.11.0
Requires-Dist: tqdm>=4.62.0
Requires-Dist: python-dotenv>=0.19.0
Provides-Extra: dev
Requires-Dist: pytest>=6.0.0; extra == "dev"
Requires-Dist: pytest-cov>=2.12.0; extra == "dev"
Requires-Dist: black>=21.0.0; extra == "dev"
Requires-Dist: flake8>=3.9.0; extra == "dev"
Requires-Dist: mypy>=0.910; extra == "dev"
Dynamic: author
Dynamic: home-page
Dynamic: requires-python
